api/__init__.py
api/auth.py
api/cache.py
api/config.py
api/constants.py
api/dependencies.py
api/distributed_cache.py
api/enhanced_grpo_gateway.py
api/enhanced_ultimate_grpo_service.py
api/errors.py
api/logging_config.py
api/main.py
api/middleware.py
api/models.py
api/observability.py
api/openapi.py
api/persistence.py
api/resilience.py
api/schemas.py
api/security.py
api/shutdown.py
api/streaming.py
api/ultimate_grpo_service.py
api/versioning.py
api/grpo/__init__.py
api/grpo/config.py
api/grpo/handlers.py
api/grpo/metrics.py
api/grpo/models.py
api/grpo/rate_limiter.py
api/grpo/router_v1.py
api/grpo/service.py
api/grpo/state.py
api/routers/__init__.py
api/routers/agents.py
api/routers/metrics.py
api/routers/training.py
api/services/__init__.py
api/services/agent_service.py
api/services/auth_service.py
api/services/training_service.py
core/__init__.py
core/adaptive_learning_controller.py
core/advanced_monitoring.py
core/agent.py
core/agent_backends.py
core/async_pool.py
core/basic_rewards.py
core/computational_engine.py
core/curriculum_learning.py
core/data_processing.py
core/domain_rewards.py
core/enhanced_state_management.py
core/environment.py
core/error_handling.py
core/evaluation.py
core/few_shot_adaptation.py
core/function_calling.py
core/input_validation.py
core/intelligent_orchestrator.py
core/memory.py
core/multi_agent_coordination.py
core/multimodal_processing.py
core/multiturn_agent.py
core/neural_architecture_search.py
core/performance_optimizer.py
core/reward.py
core/reward_base.py
core/reward_factories.py
core/rust_accelerator.py
core/structured_output.py
core/trajectory.py
core/type_system.py
core/types.py
core/value_function.py
core/enhanced/__init__.py
core/enhanced/advanced_evaluation.py
core/enhanced/advanced_rl_algorithms.py
core/enhanced/enhanced_agent.py
core/gym/__init__.py
core/gym/adapter.py
core/gym/agents.py
core/gym/mappers.py
core/gym/processors.py
environments/__init__.py
grpo_agent_framework/__init__.py
stateset_agents-0.7.1.dist-info/licenses/LICENSE
stateset_agents-0.7.1.dist-info/METADATA
stateset_agents-0.7.1.dist-info/WHEEL
stateset_agents-0.7.1.dist-info/entry_points.txt
stateset_agents-0.7.1.dist-info/top_level.txt
stateset_agents-0.7.1.dist-info/RECORD
