Metadata-Version: 2.4
Name: stateset-agents
Version: 0.7.1
Summary: Production-ready RL framework for training multi-turn conversational AI agents using GRPO and GSPO
Home-page: https://github.com/stateset/stateset-agents
Author: StateSet Team
Author-email: StateSet Team <team@stateset.ai>
License: Business Source License 1.1
Project-URL: Homepage, https://github.com/stateset/stateset-agents
Project-URL: Repository, https://github.com/stateset/stateset-agents
Project-URL: Documentation, https://stateset-agents.readthedocs.io/
Project-URL: Issues, https://github.com/stateset/stateset-agents/issues
Classifier: Development Status :: 4 - Beta
Classifier: Intended Audience :: Developers
Classifier: Intended Audience :: Science/Research
Classifier: License :: Other/Proprietary License
Classifier: Programming Language :: Python :: 3
Classifier: Programming Language :: Python :: 3.8
Classifier: Programming Language :: Python :: 3.9
Classifier: Programming Language :: Python :: 3.10
Classifier: Programming Language :: Python :: 3.11
Classifier: Programming Language :: Python :: 3.12
Classifier: Topic :: Scientific/Engineering :: Artificial Intelligence
Classifier: Framework :: FastAPI
Classifier: Environment :: GPU :: NVIDIA CUDA
Requires-Python: >=3.8
License-File: LICENSE
Requires-Dist: numpy<2.0.0,>=1.21.0
Requires-Dist: pydantic>=2.0.0
Requires-Dist: rich>=13.0.0
Requires-Dist: typer>=0.9.0
Requires-Dist: typing-extensions>=4.0.0
Requires-Dist: tqdm>=4.65.0
Provides-Extra: dev
Requires-Dist: pytest>=7.0.0; extra == "dev"
Requires-Dist: pytest-asyncio>=0.21.0; extra == "dev"
Requires-Dist: pytest-cov>=4.0.0; extra == "dev"
Requires-Dist: black>=23.0.0; extra == "dev"
Requires-Dist: isort>=5.12.0; extra == "dev"
Requires-Dist: flake8>=6.0.0; extra == "dev"
Requires-Dist: mypy>=1.0.0; extra == "dev"
Requires-Dist: pre-commit>=3.0.0; extra == "dev"
Requires-Dist: sphinx>=6.0.0; extra == "dev"
Requires-Dist: sphinx-rtd-theme>=1.2.0; extra == "dev"
Requires-Dist: ruff>=0.1.0; extra == "dev"
Requires-Dist: bandit>=1.7.0; extra == "dev"
Requires-Dist: safety>=2.0.0; extra == "dev"
Requires-Dist: semgrep>=1.0.0; extra == "dev"
Requires-Dist: torch>=2.0.0; extra == "dev"
Requires-Dist: transformers<4.45.0,>=4.30.0; extra == "dev"
Requires-Dist: datasets>=2.0.0; extra == "dev"
Requires-Dist: accelerate>=0.20.0; extra == "dev"
Requires-Dist: wandb>=0.15.0; extra == "dev"
Requires-Dist: peft>=0.4.0; extra == "dev"
Requires-Dist: trl>=0.7.0; extra == "dev"
Requires-Dist: aiohttp>=3.8.0; extra == "dev"
Requires-Dist: psutil>=5.9.0; extra == "dev"
Requires-Dist: scikit-learn<1.6.0,>=1.3.0; extra == "dev"
Provides-Extra: training
Requires-Dist: torch>=2.0.0; extra == "training"
Requires-Dist: transformers<4.45.0,>=4.30.0; extra == "training"
Requires-Dist: datasets>=2.0.0; extra == "training"
Requires-Dist: accelerate>=0.20.0; extra == "training"
Requires-Dist: wandb>=0.15.0; extra == "training"
Requires-Dist: peft>=0.4.0; extra == "training"
Requires-Dist: trl>=0.7.0; extra == "training"
Requires-Dist: aiohttp>=3.8.0; extra == "training"
Requires-Dist: psutil>=5.9.0; extra == "training"
Requires-Dist: scikit-learn<1.6.0,>=1.3.0; extra == "training"
Requires-Dist: gymnasium>=0.28.0; extra == "training"
Provides-Extra: api
Requires-Dist: fastapi>=0.110.0; extra == "api"
Requires-Dist: uvicorn>=0.23.0; extra == "api"
Provides-Extra: examples
Requires-Dist: openai>=1.0.0; extra == "examples"
Requires-Dist: anthropic>=0.5.0; extra == "examples"
Requires-Dist: langchain>=0.1.0; extra == "examples"
Provides-Extra: trl
Requires-Dist: trl>=0.7.0; extra == "trl"
Requires-Dist: bitsandbytes>=0.41.0; extra == "trl"
Provides-Extra: vllm
Requires-Dist: vllm>=0.3.0; extra == "vllm"
Provides-Extra: hpo
Requires-Dist: optuna>=3.0.0; extra == "hpo"
Requires-Dist: ray[tune]>=2.0.0; extra == "hpo"
Provides-Extra: distributed
Requires-Dist: deepspeed>=0.9.0; extra == "distributed"
Provides-Extra: full
Requires-Dist: torch>=2.0.0; extra == "full"
Requires-Dist: transformers<4.45.0,>=4.30.0; extra == "full"
Requires-Dist: datasets>=2.0.0; extra == "full"
Requires-Dist: accelerate>=0.20.0; extra == "full"
Requires-Dist: wandb>=0.15.0; extra == "full"
Requires-Dist: peft>=0.4.0; extra == "full"
Requires-Dist: trl>=0.7.0; extra == "full"
Requires-Dist: aiohttp>=3.8.0; extra == "full"
Requires-Dist: psutil>=5.9.0; extra == "full"
Requires-Dist: scikit-learn<1.6.0,>=1.3.0; extra == "full"
Requires-Dist: fastapi>=0.110.0; extra == "full"
Requires-Dist: uvicorn>=0.23.0; extra == "full"
Requires-Dist: optuna>=3.0.0; extra == "full"
Dynamic: author
Dynamic: home-page
Dynamic: license-file
Dynamic: requires-python
